smx/__init__.py
smx/compat.py
smx/compiler.py
smx/definitions.py
smx/engine.py
smx/errors.py
smx/exceptions.py
smx/include/admin.inc
smx/include/adminmenu.inc
smx/include/adt.inc
smx/include/adt_array.inc
smx/include/adt_stack.inc
smx/include/adt_trie.inc
smx/include/banning.inc
smx/include/basecomm.inc
smx/include/bitbuffer.inc
smx/include/clientprefs.inc
smx/include/clients.inc
smx/include/commandfilters.inc
smx/include/commandline.inc
smx/include/console.inc
smx/include/convars.inc
smx/include/core.inc
smx/include/cstrike.inc
smx/include/datapack.inc
smx/include/dbi.inc
smx/include/dhooks.inc
smx/include/entity.inc
smx/include/entity_prop_stocks.inc
smx/include/entitylump.inc
smx/include/events.inc
smx/include/files.inc
smx/include/float.inc
smx/include/functions.inc
smx/include/geoip.inc
smx/include/halflife.inc
smx/include/handles.inc
smx/include/helpers.inc
smx/include/keyvalues.inc
smx/include/lang.inc
smx/include/logging.inc
smx/include/mapchooser.inc
smx/include/menus.inc
smx/include/nextmap.inc
smx/include/profiler.inc
smx/include/protobuf.inc
smx/include/regex.inc
smx/include/sdkhooks.inc
smx/include/sdktools.inc
smx/include/sdktools_client.inc
smx/include/sdktools_engine.inc
smx/include/sdktools_entinput.inc
smx/include/sdktools_entoutput.inc
smx/include/sdktools_functions.inc
smx/include/sdktools_gamerules.inc
smx/include/sdktools_hooks.inc
smx/include/sdktools_sound.inc
smx/include/sdktools_stocks.inc
smx/include/sdktools_stringtables.inc
smx/include/sdktools_tempents.inc
smx/include/sdktools_tempents_stocks.inc
smx/include/sdktools_trace.inc
smx/include/sdktools_variant_t.inc
smx/include/sdktools_voice.inc
smx/include/sorting.inc
smx/include/sourcemod.inc
smx/include/string.inc
smx/include/testing.inc
smx/include/textparse.inc
smx/include/tf2.inc
smx/include/tf2_stocks.inc
smx/include/timers.inc
smx/include/topmenus.inc
smx/include/usermessages.inc
smx/include/vector.inc
smx/include/version.inc
smx/include/version_auto.inc
smx/interfaces.py
pysmx-0.4.0.dist-info/WHEEL
pysmx-0.4.0.dist-info/METADATA
pysmx-0.4.0.dist-info/RECORD
